graph_analyzer/__init__.py
graph_analyzer/analyzer.py
graph_analyzer/exceptions.py
graph_analyzer/graph_detector.py
graph_analyzer/graph_validator.py
graph_analyzer-0.1.3.dist-info/licenses/LICENSE
graph_analyzer-0.1.3.dist-info/METADATA
graph_analyzer-0.1.3.dist-info/WHEEL
graph_analyzer-0.1.3.dist-info/top_level.txt
graph_analyzer-0.1.3.dist-info/RECORD
