Metadata-Version: 2.4
Name: graph-analyzer
Version: 0.1.3
Summary: A Python package for analyzing hand-drawn graphs from images
Home-page: https://github.com/mujadid2001/graph-analyzer
Author: Hafiz Muhammad Mujadid Majeed
Author-email: Hafiz Muhammad Mujadid Majeed <mujadid2001@gmail.com>
License: MIT
Project-URL: Homepage, https://github.com/mujadid2001/graph-analyzer
Project-URL: Repository, https://github.com/mujadid2001/graph-analyzer
Project-URL: Bug Reports, https://github.com/mujadid2001/graph-analyzer/issues
Keywords: graph-theory,computer-vision,image-processing,education
Classifier: Development Status :: 4 - Beta
Classifier: Intended Audience :: Education
Classifier: Intended Audience :: Science/Research
Classifier: Topic :: Education
Classifier: Topic :: Scientific/Engineering :: Image Recognition
Classifier: Topic :: Scientific/Engineering :: Mathematics
Classifier: License :: OSI Approved :: MIT License
Classifier: Programming Language :: Python :: 3
Classifier: Programming Language :: Python :: 3.8
Classifier: Programming Language :: Python :: 3.9
Classifier: Programming Language :: Python :: 3.10
Classifier: Programming Language :: Python :: 3.11
Classifier: Programming Language :: Python :: 3.12
Requires-Python: >=3.8
License-File: LICENSE
Requires-Dist: numpy>=1.21.0
Requires-Dist: opencv-python>=4.5.0
Requires-Dist: Pillow>=8.0.0
Provides-Extra: dev
Requires-Dist: pytest>=7.0.0; extra == "dev"
Requires-Dist: pytest-cov>=3.0.0; extra == "dev"
Requires-Dist: black>=22.0.0; extra == "dev"
Requires-Dist: flake8>=4.0.0; extra == "dev"
Requires-Dist: mypy>=0.950; extra == "dev"
Requires-Dist: build>=0.7.0; extra == "dev"
Requires-Dist: twine>=4.0.0; extra == "dev"
Dynamic: author
Dynamic: home-page
Dynamic: license-file
Dynamic: requires-python
